flipjump/README.md
flipjump/__init__.py
flipjump/assembler/__init__.py
flipjump/assembler/assembler.py
flipjump/assembler/fj_parser.py
flipjump/assembler/inner_classes/__init__.py
flipjump/assembler/inner_classes/expr.py
flipjump/assembler/inner_classes/ops.py
flipjump/assembler/preprocessor.py
flipjump/fjm/__init__.py
flipjump/fjm/fjm_consts.py
flipjump/fjm/fjm_reader.py
flipjump/fjm/fjm_writer.py
flipjump/flipjump_cli.py
flipjump/flipjump_quickstart.py
flipjump/interpretter/__init__.py
flipjump/interpretter/debugging/__init__.py
flipjump/interpretter/debugging/breakpoints.py
flipjump/interpretter/debugging/macro_usage_graph.py
flipjump/interpretter/debugging/message_boxes.py
flipjump/interpretter/fjm_run.py
flipjump/interpretter/io_devices/BrokenIO.py
flipjump/interpretter/io_devices/FixedIO.py
flipjump/interpretter/io_devices/IODevice.py
flipjump/interpretter/io_devices/StandardIO.py
flipjump/interpretter/io_devices/__init__.py
flipjump/py.typed
flipjump/stl/README.md
flipjump/stl/bit/casting.fj
flipjump/stl/bit/cond_jumps.fj
flipjump/stl/bit/div.fj
flipjump/stl/bit/input.fj
flipjump/stl/bit/logics.fj
flipjump/stl/bit/math.fj
flipjump/stl/bit/memory.fj
flipjump/stl/bit/mul.fj
flipjump/stl/bit/output.fj
flipjump/stl/bit/pointers.fj
flipjump/stl/bit/shifts.fj
flipjump/stl/casting.fj
flipjump/stl/conf.json
flipjump/stl/hex/cond_jumps.fj
flipjump/stl/hex/div.fj
flipjump/stl/hex/input.fj
flipjump/stl/hex/logics.fj
flipjump/stl/hex/math.fj
flipjump/stl/hex/math_basic.fj
flipjump/stl/hex/memory.fj
flipjump/stl/hex/mul.fj
flipjump/stl/hex/output.fj
flipjump/stl/hex/pointers/basic_pointers.fj
flipjump/stl/hex/pointers/pointer_arithmetics.fj
flipjump/stl/hex/pointers/read_pointers.fj
flipjump/stl/hex/pointers/stack.fj
flipjump/stl/hex/pointers/write_pointers.fj
flipjump/stl/hex/pointers/xor_from_pointer.fj
flipjump/stl/hex/pointers/xor_to_pointer.fj
flipjump/stl/hex/shifts.fj
flipjump/stl/hex/tables_init.fj
flipjump/stl/ptrlib.fj
flipjump/stl/runlib.fj
flipjump-1.3.0.dist-info/LICENSE
flipjump-1.3.0.dist-info/METADATA
flipjump-1.3.0.dist-info/WHEEL
flipjump-1.3.0.dist-info/entry_points.txt
flipjump-1.3.0.dist-info/RECORD
