Metadata-Version: 2.3
Name: flipjump
Version: 1.3.0
Summary: The single instruction language - Flip a bit, then Jump
Home-page: https://esolangs.org/wiki/FlipJump
License: BSD-2-Clause-Simplified
Keywords: esolang,oisc,assembly
Author: Tom Herman
Author-email: flipjumpproject@gmail.com
Requires-Python: >=3.8.1,<4.0.0
Classifier: Intended Audience :: Developers
Classifier: Intended Audience :: Education
Classifier: Intended Audience :: Science/Research
Classifier: License :: Other/Proprietary License
Classifier: Operating System :: OS Independent
Classifier: Programming Language :: Other
Classifier: Programming Language :: Python :: 3
Classifier: Programming Language :: Python :: 3.9
Classifier: Programming Language :: Python :: 3.10
Classifier: Programming Language :: Python :: 3.11
Classifier: Programming Language :: Python :: 3.12
Classifier: Programming Language :: Python :: 3.13
Classifier: Programming Language :: Python :: 3.8
Classifier: Topic :: Education
Classifier: Topic :: Software Development :: Assemblers
Classifier: Topic :: Software Development :: Compilers
Classifier: Topic :: Software Development :: Debuggers
Classifier: Topic :: Software Development :: Interpreters
Classifier: Topic :: Software Development :: Libraries
Provides-Extra: stats
Provides-Extra: tests
Requires-Dist: bandit (>=1.7.6,<2.0.0) ; extra == "tests"
Requires-Dist: black (>=24.8.0,<25.0.0) ; extra == "tests"
Requires-Dist: easygui (>=0.98.3,<0.99.0)
Requires-Dist: flake8 (>=6.1.0,<7.0.0) ; extra == "tests"
Requires-Dist: mypy (>=1.7.1,<2.0.0) ; extra == "tests"
Requires-Dist: plotly (>=5.16.1,<6.0.0) ; extra == "stats"
Requires-Dist: pytest (>=7.4.0,<8.0.0) ; extra == "tests"
Requires-Dist: pytest-ordering (>=0.6,<0.7) ; extra == "tests"
Requires-Dist: pytest-xdist (>=3.3.1,<4.0.0) ; extra == "tests"
Requires-Dist: sly (>=0.4,<0.5)
Requires-Dist: tox (>=4.11.4,<5.0.0) ; extra == "tests"
Project-URL: Documentation, https://github.com/tomhea/flip-jump/wiki
Project-URL: Repository, https://github.com/tomhea/flip-jump
